EMpy_gpu/RCWA.py
EMpy_gpu/__init__.py
EMpy_gpu/constants.py
EMpy_gpu/devices.py
EMpy_gpu/materials.py
EMpy_gpu/scattering.py
EMpy_gpu/transfer_matrix.py
EMpy_gpu/utils.py
EMpy_gpu/version.py
EMpy_gpu/modesolvers/FD.py
EMpy_gpu/modesolvers/FMM.py
EMpy_gpu/modesolvers/__init__.py
EMpy_gpu/modesolvers/geometries.py
EMpy_gpu/modesolvers/interface.py
tests/__init__.py
tests/materials_test.py
tests/utils_test.py
ElectroMagneticPythonGpu-0.0.0.dist-info/LICENSE
ElectroMagneticPythonGpu-0.0.0.dist-info/METADATA
ElectroMagneticPythonGpu-0.0.0.dist-info/WHEEL
ElectroMagneticPythonGpu-0.0.0.dist-info/top_level.txt
ElectroMagneticPythonGpu-0.0.0.dist-info/RECORD
