Metadata-Version: 2.1
Name: ElectroMagneticPythonGpu
Version: 0.0.0
Summary: EMpy - ElectroMagnetic Python
Home-page: http://lbolla.github.io/EMpy/
Author: Lorenzo Bolla
Author-email: code@lbolla.info
License: BSD
Download-URL: https://github.com/lbolla/EMpy
Platform: Windows
Platform: Linux
Platform: Mac OS-X
Classifier: Development Status :: 4 - Beta
Classifier: Environment :: Console
Classifier: Intended Audience :: Science/Research
Classifier: License :: OSI Approved :: BSD License
Classifier: Natural Language :: English
Classifier: Programming Language :: Python :: 3.6
Classifier: Operating System :: OS Independent
Classifier: Topic :: Scientific/Engineering :: Physics
Provides: EMpy
License-File: LICENSE
Requires-Dist: future
Requires-Dist: numpy
Requires-Dist: scipy
Requires-Dist: matplotlib
